{
  "id": "hLU-h-UWnd",
  "version": "0.0.0",
  "games": {
    "jVF1D_0s": {
      "id": "jVF1D_0s",
      "boardObjectsArrays": ["object-pair"],
      "name": "order1",
      "ruleArray": "mDiksQ5N"
    },
    "mlA01o-P": {
      "id": "mlA01o-P",
      "boardObjectsArrays": ["object-pair"],
      "name": "rule-order1-reversed",
      "ruleArray": "-lpa65sl"
    },
    "counter": {
      "id": "counter",
      "boardObjectsArrays": ["corners"],
      "name": "counter",
      "ruleArray": "counter"
    },
    "shape": {
      "id": "shape",
      "boardObjectsArrays": ["corners"],
      "name": "shape",
      "ruleArray": "shape"
    },
    "color": {
      "id": "color",
      "boardObjectsArrays": ["corners"],
      "name": "color",
      "ruleArray": "color"
    },
    "position": {
      "id": "position",
      "boardObjectsArrays": ["corners"],
      "name": "position",
      "ruleArray": "position"
    },
    "first-previous": {
      "id": "first-previous",
      "boardObjectsArrays": ["corners"],
      "name": "first-previous",
      "ruleArray": "first-previous"
    },
    "first-previous-shape": {
      "id": "first-previous-shape",
      "boardObjectsArrays": ["corners"],
      "name": "first-previous-shape",
      "ruleArray": "first-previous-shape"
    },
    "first-previous-color": {
      "id": "first-previous-color",
      "boardObjectsArrays": ["corners"],
      "name": "first-previous-color",
      "ruleArray": "first-previous-color"
    },
    "first-previous-color-shape": {
      "id": "first-previous-color-shape",
      "boardObjectsArrays": ["corners"],
      "name": "first-previous-color-shape",
      "ruleArray": "first-previous-color-shape"
    },
    "previous": {
      "id": "previous",
      "boardObjectsArrays": ["corners"],
      "name": "previous",
      "ruleArray": "previous"
    },
    "previous-shape": {
      "id": "previous-shape",
      "boardObjectsArrays": ["corners"],
      "name": "previous-shape",
      "ruleArray": "previous-shape"
    },
    "previous-color": {
      "id": "previous-color",
      "boardObjectsArrays": ["corners"],
      "name": "previous-color",
      "ruleArray": "previous-color"
    },
    "previous-color-shape": {
      "id": "previous-color-shape",
      "boardObjectsArrays": ["corners"],
      "name": "previous-color-shape",
      "ruleArray": "previous-color-shape"
    },
    "clockwise": {
      "id": "clockwise",
      "boardObjectsArrays": ["corners"],
      "name": "clockwise",
      "ruleArray": "clockwise"
    }
  },
  "ruleArrays": {
    "counter": {
      "id": "counter",
      "stringified": "(2,*,*,*,*)\n(1,*,*,*,*)",
      "name": "counter"
    },
    "shape": {
      "id": "shape",
      "stringified": "(2,square,*,*,*)\n(1,circle,*,*,*)",
      "name": "shape"
    },
    "color": {
      "id": "color",
      "stringified": "(1,*,yellow,*,*)\n(1,*,red,*,*)",
      "name": "color"
    },
    "position": {
      "id": "position",
      "stringified": "(1,*,*,1,*)\n(1,*,*,6,*)\n(1,*,*,31,*)\n(1,*,*,36,*)",
      "name": "position"
    },
    "first-previous": {
      "id": "first-previous",
      "stringified": "(1,*,*,*,[p])",
      "name": "first-previous"
    },
    "first-previous-shape": {
      "id": "first-previous-shape",
      "stringified": "(1,*,*,*,[ps])",
      "name": "first-previous-shape"
    },
    "first-previous-color": {
      "id": "first-previous-color",
      "stringified": "(1,*,*,*,[pc])",
      "name": "first-previous-color"
    },
    "first-previous-color-shape": {
      "id": "first-previous-color-shape",
      "stringified": "(1,*,*,*,[pcs])",
      "name": "first-previous-color-shape"
    },
    "previous": {
      "id": "previous",
      "stringified": "(1,*,*,*,*)\n(1,*,*,*,[p])",
      "name": "previous"
    },
    "previous-shape": {
      "id": "previous-shape",
      "stringified": "(1,*,*,*,*)\n(1,*,*,*,[ps])",
      "name": "previous-shape"
    },
    "previous-color": {
      "id": "previous-color",
      "stringified": "(1,*,*,*,*)\n(1,*,*,*,[pc])",
      "name": "previous-color"
    },
    "previous-color-shape": {
      "id": "previous-color-shape",
      "stringified": "(1,*,*,*,*)\n(1,*,*,*,[pcs])",
      "name": "previous-color-shape"
    },
    "full-match": {
      "id": "full-match",
      "stringified": "(1,square,blue,1,*)",
      "name": "full-match"
    },
    "clockwise": {
      "id": "clockwise",
      "stringified": "(1,*,*,*,*)\n(*,*,*,*,[(p+1)%4])",
      "name": "clockwise"
    },
    "mDiksQ5N": {
      "id": "mDiksQ5N",
      "stringified": "(*,*,*,*,*)",
      "name": "rule-order1",
      "order": [
        0,
        1,
        2,
        3,
        4,
        5,
        6,
        7,
        8,
        9,
        10,
        11,
        12,
        13,
        14,
        15,
        16,
        17,
        18,
        19,
        20,
        21,
        22,
        23,
        24,
        25,
        26,
        27,
        28,
        29,
        31,
        31,
        32,
        33,
        34,
        35
      ]
    },
    "-lpa65sl": {
      "id": "-lpa65sl",
      "stringified": "(*,*,*,*,*)",
      "name": "rule-order-1-reversed",
      "order": [
        35,
        34,
        33,
        32,
        31,
        31,
        29,
        28,
        27,
        26,
        25,
        24,
        23,
        22,
        21,
        20,
        19,
        18,
        17,
        16,
        15,
        14,
        13,
        12,
        11,
        10,
        9,
        8,
        7,
        6,
        5,
        4,
        3,
        2,
        1,
        0
      ]
    }
  },
  "boardObjectsArrays": {
    "object-pair": {
      "id": "object-pair",
      "value": [
        {
          "color": "red",
          "id": "1",
          "shape": "square",
          "x": 1,
          "y": 2
        },
        {
          "color": "blue",
          "id": "2",
          "shape": "circle",
          "x": 2,
          "y": 3
        }
      ],
      "name": "objects-order1"
    },
    "corners": {
      "id": "corners",
      "value": [
        {
          "color": "yellow",
          "id": "yellow-square-1",
          "shape": "square",
          "x": 1,
          "y": 1
        },
        {
          "color": "blue",
          "id": "blue-circle-31",
          "shape": "circle",
          "x": 1,
          "y": 6
        },
        {
          "color": "red",
          "id": "red-square-6",
          "shape": "square",
          "x": 6,
          "y": 1
        },
        {
          "color": "red",
          "id": "red-square-36",
          "shape": "square",
          "x": 6,
          "y": 6
        }
      ],
      "name": "objects-order1"
    }
  }
}
